classy_decorators/__init__.py
classy_decorators/decorators.py
classy_decorators/function_types.py
examples/__init__.py
examples/double.py
examples/inheritance.py
examples/multiply.py
classy_decorators-1.2.0.dist-info/LICENSE
classy_decorators-1.2.0.dist-info/METADATA
classy_decorators-1.2.0.dist-info/WHEEL
classy_decorators-1.2.0.dist-info/top_level.txt
classy_decorators-1.2.0.dist-info/RECORD
