Metadata-Version: 2.1
Name: classy-decorators
Version: 1.2.0
Summary: Hassle-free creation of decorators for functions and methods, OO-style.
Home-page: https://github.com/jorenham/classy-decorators/
Author: Joren Hammudoglu
License: UNKNOWN
Platform: UNKNOWN
Classifier: Intended Audience :: Developers
Classifier: Topic :: Software Development :: Libraries :: Python Modules
Classifier: Programming Language :: Python :: 3
Classifier: License :: OSI Approved :: GNU General Public License v3 (GPLv3)
Classifier: Operating System :: POSIX
Requires-Python: >=3.8.0
Provides-Extra: typeguard
Requires-Dist: typeguard ; extra == 'typeguard'
